remotemodels
