Metadata-Version: 1.1
Name: remotemodels
Version: 0.6.3
Summary: Declarative dictionary-based model classes for Python
Home-page: https://github.com/tzangms/remotemodels/
Author: Ming Hsien Tzang
Author-email: tzangms@gmail.com
License: Public Domain
Platform: UNKNOWN
Classifier: Programming Language :: Python
Classifier: Development Status :: 3 - Alpha
Classifier: Intended Audience :: Developers
Classifier: License :: Public Domain
Classifier: Operating System :: OS Independent
Classifier: Topic :: Software Development :: Libraries :: Python Modules
